mslarkin/__init__.py
mslarkin/gcp_utils.py
mslarkin/gunicorn_app.py
mslarkin/load_gen_tools.py
mslarkin/run_utils.py
mslarkin/tools.py
mslarkin_utils-1.68.dist-info/METADATA
mslarkin_utils-1.68.dist-info/WHEEL
mslarkin_utils-1.68.dist-info/top_level.txt
mslarkin_utils-1.68.dist-info/RECORD
