Metadata-Version: 2.1
Name: mslarkin-utils
Version: 1.68
Summary: Frequently used utilities for Python
Keywords: mslarkin
Requires-Python: >=3.8
Requires-Dist: requests
Requires-Dist: google-cloud-pubsub
Requires-Dist: google-cloud-monitoring
Requires-Dist: google-cloud-run
Requires-Dist: gunicorn
Requires-Dist: pytz
Requires-Dist: psutil
